looger-0.3.dist-info/METADATA
looger-0.3.dist-info/WHEEL
looger-0.3.dist-info/licenses/LICENSE
looger/loglib.pyi
looger/__init__.py
looger/loglib.cpython-312-darwin.so
looger-0.3.dist-info/RECORD
