Metadata-Version: 2.3
Name: looger
Version: 0.3
Requires-Dist: maturin
License-File: LICENSE
Summary: logging lib for python with a rust backend for faster results. Or should I say looger?
Project-URL: GitHub, https://github.com/d33p0st/looger
